README.md
setup.py
listrindex/__init__.py
listrindex.egg-info/PKG-INFO
listrindex.egg-info/SOURCES.txt
listrindex.egg-info/dependency_links.txt
listrindex.egg-info/top_level.txt