Metadata-Version: 2.4
Name: listrindex
Version: 0.1
Summary: Helps to find the last index of the element in list
Home-page: https://github.com/VoyagerX21/listrindex
Author: Gourav Khakse
Author-email: khakse2gaurav2003@gmail.com
Classifier: Programming Language :: Python :: 3
Dynamic: author
Dynamic: author-email
Dynamic: classifier
Dynamic: description
Dynamic: description-content-type
Dynamic: home-page
Dynamic: summary
